{"title":"「密」フェス問題、第三者委員による検証つづき１８歳以上！","author":"mong2","description":"委員長「後ろから押さないでください！先っちょが密っちゃいます！」<br>前の密フェスundefinedundefined<aundefinedhref='https://ecchi.iwara.tv/videos/mj9oecbe5mc85lwom'>https://ecchi.iwara.tv/videos/mj9oecbe5mc85lwom</a>","thumb":"//i.iwara.tv/sites/default/files/styles/thumbnail/public/videos/thumbnails/2177095/thumbnail-2177095_0008.jpg?itok=Oi5WThxE","download":"https://ecchi.iwara.tv/api/video/brnv6u0ewmuldv5ye","origin":"https://ecchi.iwara.tv/videos/brnv6u0ewmuldv5ye"}