{"title":"【艦これ肉便器】由良１８歳以上！","author":"宗教団体真メグデス","description":"宗教団体真メグデスの活動は、アルバムの売り上げで賄われております。皆様、応援よろしくお願いいたします！<br><aundefinedhref='https://www.dlsite.com/maniax/circle/profile/=/maker_id/RG45495.html'>https://www.dlsite.com/maniax/circle/profile/=/maker_id/RG45495.html</a>","thumb":"//i.iwara.tv/sites/default/files/styles/thumbnail/public/videos/thumbnails/2205029/thumbnail-2205029_0001.jpg?itok=OPuc_PGG","download":"https://ecchi.iwara.tv/api/video/g6qmgud6oqfovvylb","origin":"https://ecchi.iwara.tv/videos/g6qmgud6oqfovvylb"}