{"title":"【R-18:MMD】兎之テンカさんがフタリボシでハジけてた１８歳以上！","author":"TubeP","description":"文化祭のクラス出し物の喫茶で、バニー姿で給仕してアヘりたい願望をお持ちの兎之テンカさん（学級委員長）です。<br>ちなみにミルクと砂糖は無料で、お客様から要望があれば、青いほうからミルクを、赤いほうから砂糖（シロップ）を提供するとのこと。<br>青いほうはぐいっと握り潰して絞ればいいらしいです。<br>赤いほうは‥腹パンでもするんですかねぇ（適当）。<br>テンカさんは鬼畜プレイ大好きとのことです。","thumb":"//i.iwara.tv/sites/default/files/styles/thumbnail/public/videos/thumbnails/2250065/thumbnail-2250065_0011.jpg?itok=ucCJqsOc","download":"https://ecchi.iwara.tv/api/video/m9o88ckwbho1nwrj","origin":"https://ecchi.iwara.tv/videos/m9o88ckwbho1nwrj"}