{"title":"Honkai Impact 3-Bronya-警服大板鸭的摇臀哦-Mister１８歳以上！","author":"在下神奈有何贵干","description":"感谢收看！<br>Thankundefinedyouundefinedforundefinedwatching!<br>想要小红心qwq！！<br>~欢迎加入神奈的QQ交流群：816370769<br>↓↓↓↓<br>获取4KundefinedHDundefined<aundefinedhref='https://afdian.net/'>https://afdian.net/</a>@zaixiashennai103<br>4KundefinedHDundefined<aundefinedhref='https://www.patreon.com/ZXSN_MMD'>https://www.patreon.com/ZXSN_MMD</a>","thumb":"//i.iwara.tv/sites/default/files/styles/thumbnail/public/videos/thumbnails/2242618/thumbnail-2242618_0010.jpg?itok=cc5Lfgqi","download":"https://ecchi.iwara.tv/api/video/nz12ahzozwhpeo8yb","origin":"https://ecchi.iwara.tv/videos/nz12ahzozwhpeo8yb"}