{"title":"【おしっこ】とびだせとうほくの山 /  東北イタコ・ずん子・きりたん【ｺｯｼｮﾘ】[Itako・Zunko・Kiritan]１８歳以上！","author":"Aldebaran","description":"<spanundefinedstyle='font-weight:bold'>Notice:Thisundefinedvidundefinedhasundefinedpeeing-scene.<br>こ、この曲はもしや...そう、おしっこ注意です</span>","thumb":"//i.iwara.tv/sites/default/files/styles/thumbnail/public/videos/thumbnails/2282621/thumbnail-2282621_0013.jpg?itok=eFNcEcaV","download":"https://ecchi.iwara.tv/api/video/omglliworh1pymej","origin":"https://ecchi.iwara.tv/videos/omglliworh1pymej"}