{"title":"恋乃夜舞×罪袋×insects…….１８歳以上！","author":"超级喵杀拳","description":"(undefined˙-˙undefined)<br>红p已炸，谢谢你(๑❛ᴗ❛๑)<br>嗯，没啥了。就这样吧，视频里有个小问题，锁链出现了1-2秒，唉，导出时没发现(ー`´ー)<br>下期是艾米莉亚吧，大概。做了5个月的爱发电额外视频，我知道自己做的超级一般，所以到现在为止，爱发电最高发电额也才15软妹币。5个月啊（undefined’undefined-undefined’undefined*undefined)<br>当然，定制不算。","thumb":"//i.iwara.tv/sites/default/files/styles/thumbnail/public/videos/thumbnails/2175360/thumbnail-2175360_0002.jpg?itok=jhUJ_se6","download":"https://ecchi.iwara.tv/api/video/vm8lyurqweieqvqkv","origin":"https://ecchi.iwara.tv/videos/vm8lyurqweieqvqkv"}