{"title":"[FAP HERO]門を開く者アリス で 蹲踞ポールダンス ぐぱぁVer.１８歳以上！","author":"FHID00","description":"Originalundefinedvideoundefinedby:undefinedJYB_UNKNOWN<br>Channelundefinedaddress:undefined<aundefinedhref='https://ecchi.iwara.tv/users/jybunknown'>https://ecchi.iwara.tv/users/jybunknown</a>","thumb":"//i.iwara.tv/sites/default/files/styles/thumbnail/public/videos/thumbnails/2242327/thumbnail-2242327_0008.jpg?itok=VyuzQDKe","download":"https://ecchi.iwara.tv/api/video/wxeyzurgegcqemyrk","origin":"https://ecchi.iwara.tv/videos/wxeyzurgegcqemyrk"}