{"title":"【R-18】Kancolle_Maya_3P１８歳以上！","author":"Luxu","description":"乱交系です。<br>■Fantiaundefined【R-18】Kancolle_摩耶3P【PmmundefinedDL＆MotionundefinedDL】<br>Supportundefinedme!<br><aundefinedhref='https://fantia.jp/fanclubs/23328'>https://fantia.jp/fanclubs/23328</a>","thumb":"//i.iwara.tv/sites/default/files/styles/thumbnail/public/videos/thumbnails/2349696/thumbnail-2349696_0007.jpg?itok=fUfBYPN-","download":"https://ecchi.iwara.tv/api/video/zmoj7fyxz2fk0x202","origin":"https://ecchi.iwara.tv/videos/zmoj7fyxz2fk0x202"}