{"title":"恋ダンス　橙・あぴミクセーラー","author":"kotobuki_risa","description":"４Ｋ版：undefined<aundefinedhref='https://youtu.be/5iHXgZ92wZc'>https://youtu.be/5iHXgZ92wZc</a><br>あぴミクちゃんと橙ちゃんがセーラー服で恋ダンスを踊ります！２人のセーラー少女のパンチラダンスをお楽しみください！<br>Songundefined:undefined星野undefined源undefined-undefined恋(SouさんundefinedCover)","thumb":"//i.iwara.tv/sites/default/files/styles/thumbnail/public/videos/thumbnails/840045/thumbnail-840045_0011.jpg?itok=_0-WFFNS","download":"https://www.iwara.tv/api/video/1j7jqizqams3e9kw6","origin":"https://www.iwara.tv/videos/1j7jqizqams3e9kw6"}