{"title":"【MMD】てとらーず２人がミニセーラー服で30sexyを踊る","author":"昭和懐古おやぢ","description":"undefined元々が男性向けmotion「トレスはAZ様の学バサ猿飛佐助（戦国BASARA）<br>なのでこれをうら若き女の子に踊ってもらいながら昭和懐古おやぢ<br>のカメラ??で撮るとえらいことに（エロい？？）ことになります。<br>これだけモーションが激しいので、いつものてとらちゃんより気持ち<br>ほんの少しだけですが長いスカート(それでも充分にミニですが）で<br>踊ってもらいましたが、とってもいい感じでした。<br>undefined元のモーションがそうなのですが、ミニの女の子に踊ってもらって<br>各所で見られる腰を落とした状態での異様なまでの足の開閉！！！<br>これはおやぢとしては絶対に外せないのでガン見（ガン撮り）させて<br>頂きました。","thumb":"//i.iwara.tv/sites/default/files/styles/thumbnail/public/videos/thumbnails/478625/thumbnail-478625_0003.jpg?itok=rOblaDkP","download":"https://www.iwara.tv/api/video/a2gmkha0gzt8zlywa","origin":"https://www.iwara.tv/videos/a2gmkha0gzt8zlywa"}