{"title":"【ＭＭＤ】ガルパンのメンバーが制服で階段の上であんこう踊りをする","author":"昭和懐古おやぢ","description":"undefined2020年最初はてとらーず、アマガミ、渋谷凛ちゃん達に着もので<br>これを踊ってもらいましたが、三が日も終わって明日が最後の日曜日<br>（カレンダー通りで働ける幸せな人々は）ってわけでそろそろ普段の<br>生活に戻る前に（明日RESETして下さいませ(笑)）最後ぶったるんだ<br>雰囲気であんこう鍋と言えば大洗と言えばやっぱりガルパンの面々<br>（その割に偏っています(笑)）踊って頂く事にしました。<br>最近艦これの投稿も続いたしねぇ・・・","thumb":"//i.iwara.tv/sites/default/files/styles/thumbnail/public/videos/thumbnails/712312/thumbnail-712312_0001.jpg?itok=sk48Tlki","download":"https://www.iwara.tv/api/video/aynoafa0gzt84zv7j","origin":"https://www.iwara.tv/videos/aynoafa0gzt84zv7j"}