{"title":"【MMD Realistic】Genshin Impact  - Raiden Shogun x Eula Lawrence - Dancing in nightgown - Nincha【18】","author":"RaidenLolita","description":"R18undefinedverundefinedon:undefined<aundefinedhref='https://www.patreon.com/posts/58966017'>https://www.patreon.com/posts/58966017</a>","thumb":"//i.iwara.tv/sites/default/files/styles/thumbnail/public/video_embed_field_thumbnails/youtube/IYywXazXopY.jpg?itok=HFmuzwXI","download":"https://www.iwara.tv/api/video/ekal9hal6ztmz60kj","origin":"https://www.iwara.tv/videos/ekal9hal6ztmz60kj"}