{"title":"【MMD】金剛型４人がイレヴンレイヴガールを踊る","author":"昭和懐古おやぢ","description":"◆モーションと曲<br>エバさんがundefined2016/05/25に作成された<br>【MMD銀魂】イレヴンレイヴガール【モーショントレース】<br><aundefinedhref='http://www.nicovideo.jp/watch/sm28914962'>http://www.nicovideo.jp/watch/sm28914962</a>","thumb":"//i.iwara.tv/sites/default/files/styles/thumbnail/public/videos/thumbnails/690150/thumbnail-690150_0005.jpg?itok=ENL7GqkN","download":"https://www.iwara.tv/api/video/evr77hmbgzsmax2mo","origin":"https://www.iwara.tv/videos/evr77hmbgzsmax2mo"}