{"title":"[MMD MMDm@ster] Happy Halloween - Haruka, Ami, Mami (Nightmareblood) [1440p60 W]","author":"Markus7P","description":"MMD,undefined<aundefinedhref='mailto:MMDM@STER'>MMDM@STER</a>undefinedvideo:undefinedHaruka,undefinedAmi,undefinedMamiundefined-undefinedHappyundefinedHalloween<br>Costume:undefinedNightmarebloodundefined&apos;Standard&apos;undefinedver.","thumb":"//i.iwara.tv/sites/default/files/styles/thumbnail/public/video_embed_field_thumbnails/youtube/tf_QSsn4RH4.jpg?itok=sHMEbnXh","download":"https://www.iwara.tv/api/video/ga5nnckvou7ymy2o","origin":"https://www.iwara.tv/videos/ga5nnckvou7ymy2o"}