{"title":"【MMDm@​ster】はるゆきによる特別ステージ配信動画（紳士向け）","author":"星影光一","description":"コロナウイルスの影響により、卒業式の特別ステージが中止になってしまったため。急遽動画配信という形を卒業生をお祝いします。<br>雪歩は好き！雪！本気マジックを<br>春香は恋はきっと急上昇☆を踊っていただきました。<br>卒業生の皆さんこれで少しは思い出に残るステージにしてください。<br>二人とも破壊力抜群です。<br>【MMDm@​ster】はるゆきによる特別ステージ配信動画（紳士向け）","thumb":"//i.iwara.tv/sites/default/files/styles/thumbnail/public/video_embed_field_thumbnails/youtube/jx8XbgluCRE.jpg?itok=8UqzuJqf","download":"https://www.iwara.tv/api/video/grpaahwljaiok6717","origin":"https://www.iwara.tv/videos/grpaahwljaiok6717"}