{"title":"愛言葉Ⅲ　ロリ小悪魔 JKカーディガン","author":"kotobuki_risa","description":"Youtubeundefinedlink:undefined<aundefinedhref='https://youtu.be/Ear2S2G6DyQ'>https://youtu.be/Ear2S2G6DyQ</a><br>水華さんの動画に登場したロリ小悪魔ちゃんに一目惚れし、つい、妖夢ちゃんボディと融合し、JKモデル（JCかも？）を作ってしまいました。パンツも彼女のために今までの素材を活用し、かわいくできましたので、ここに披露します。曲は「愛言葉Ⅲ」。何人もの女の子がパンツを惜しげもなく披露したモーション、カメラです。最後までお楽しみいただけると嬉しいです。","thumb":"//i.iwara.tv/sites/default/files/styles/thumbnail/public/videos/thumbnails/754941/thumbnail-754941_0005.jpg?itok=Rn4wSmky","download":"https://www.iwara.tv/api/video/k25y7hqxdmizajd3o","origin":"https://www.iwara.tv/videos/k25y7hqxdmizajd3o"}