{"title":"[MMD] Star Wars Dumdi Dumdi Jyn Also MMD R-18 Sexy Star Wars","author":"jurihan","description":"FULLundefinedVIDEOundefinedHERE<br><aundefinedhref='https://www.patreon.com/posts/46763811'>https://www.patreon.com/posts/46763811</a><br>MODELundefinedDLundefinedHERE<br><aundefinedhref='https://www.patreon.com/posts/mmd-sta'>https://www.patreon.com/posts/mmd-sta</a>...","thumb":"//i.iwara.tv/sites/default/files/styles/thumbnail/public/video_embed_field_thumbnails/youtube/-jaW9Fi9ESk.jpg?itok=Kwb_i2zr","download":"https://www.iwara.tv/api/video/koz66f1q65hzrjgr6","origin":"https://www.iwara.tv/videos/koz66f1q65hzrjgr6"}