{"title":"【Azur MMD】 St. Louis - phone number(폰넘버) R18","author":"LTC_Raven","description":"motion,undefinedcameraundefinedbyundefinedureshiiiiii<br><aundefinedhref='https://www.youtube.com/watch?v=MnMiNEwvXy4'>https://www.youtube.com/watch?v=MnMiNEwvXy4</a>","thumb":"//i.iwara.tv/sites/default/files/styles/thumbnail/public/video_embed_field_thumbnails/youtube/pApvnOO-fTI.jpg?itok=-IYvfNgn","download":"https://www.iwara.tv/api/video/ln01wfv4kfw7myre","origin":"https://www.iwara.tv/videos/ln01wfv4kfw7myre"}