{"title":"【MMD】5ミライアカリ、てとらーず、本人が姉ヶ崎寧々さんセーラー服でゆっきゆっきゆっきダンスを踊るモーションずらし","author":"昭和懐古おやぢ","description":"undefinedライクーP様が2014年に作成されたモーションを使わせて頂きました。<br>ものすごく素敵なTurnが多くてこれはもう単純に横嶋（邪）目的に最高<br>なモーションじゃないかとピンと来ました。<br>undefinedっていうわけで<br>１作目てとらーずのセーラー服undefinedundefined２作目鈴熊学園制服<br>３作目テニスウエアundefinedundefinedundefinedundefinedundefinedundefinedundefined４作目ちょっと長めの膝丈スカート<br>undefinedに続いて５作目は挙動の素敵な姉ヶ崎寧々さんのセーラー服での投稿です。","thumb":"//i.iwara.tv/sites/default/files/styles/thumbnail/public/videos/thumbnails/769807/thumbnail-769807_0005.jpg?itok=6nbhUlH6","download":"https://www.iwara.tv/api/video/m4lqohqb8zi8ryq6o","origin":"https://www.iwara.tv/videos/m4lqohqb8zi8ryq6o"}