{"title":"【MMD】てとらーず4人ミニセーラー服が駅ノロビーで鋲心全壊ガールを踊る","author":"昭和懐古おやぢ","description":"おやぢにとっては初めてのモーションとなります。<br>キリカさんが10/1に配布されたばかりの新作です。<br>以下のような解説がついております。<br>◆原曲◆<br>【GUMI】鋲心全壊ガール【オリジナルMV】<br>undefined<aundefinedhref='https://www.nicovideo.jp/watch/sm32047180'>https://www.nicovideo.jp/watch/sm32047180</a>","thumb":"//i.iwara.tv/sites/default/files/styles/thumbnail/public/videos/thumbnails/646719/thumbnail-646719_0001.jpg?itok=74m3m8oc","download":"https://www.iwara.tv/api/video/ng2gysmgpziprv42l","origin":"https://www.iwara.tv/videos/ng2gysmgpziprv42l"}