{"title":"【MMD R-18】 iMarine Project - Marine Bloomin' [REMASTER 2019] | Maran Valkyrie, Mage, Aries 【4k60fps】","author":"MMDNecrox","description":"▼undefinedYoutube:undefined<aundefinedhref='https://www.youtube.com/c/MMDNecrox2'>https://www.youtube.com/c/MMDNecrox2</a><br>➝undefinedTwitter:undefined<aundefinedhref='https://twitter.com/MMDNecrox'>https://twitter.com/MMDNecrox</a><br>➝undefinedServerundefinedDiscord:undefined<aundefinedhref='https://discord.gg/tMPggeR'>https://discord.gg/tMPggeR</a><br>▼undefinedSupport:undefined<aundefinedhref='https://www.patreon.com/mmdnecrox'>https://www.patreon.com/mmdnecrox</a>","thumb":"//i.iwara.tv/sites/default/files/styles/thumbnail/public/video_embed_field_thumbnails/youtube/mB_FR_rxU5w.jpg?itok=zy8Itfc4","download":"https://www.iwara.tv/api/video/o1ya4sqo2s1zobnm","origin":"https://www.iwara.tv/videos/o1ya4sqo2s1zobnm"}