{"title":"[R-13] [Niconi Solid] Wave","author":"Xnqn","description":"[R13]undefinedprototypeundefinedrender.undefinedtestingundefinednewundefinedfxundefinedset.undefinedAnamorphicundefinedCinemascopeundefined2.39:1undefined720p/60fps<br>songundefined:undefinedundefinedwaveundefined[Reolundefined-undefinedNikiundefined-undefinedEZFG]undefinedwatch?v=36SxEHQeDi8<br>motionundefined:undefinedtwitter@aimonoya1<br>modelundefined:undefined<aundefinedhref='http://3d.nicovideo.jp/alicia/'>http://3d.nicovideo.jp/alicia/</a><br>stageundefined:undefinedundefinedtwitter@mitsuran5<br>fxundefined:undefined<aundefinedhref='mailto:twitter@BeamManP'>twitter@BeamManP</a>undefined,undefinedtwitter@ikeno_mmdundefined,undefinedtwitter@sovoro_mmdundefined,undefinedtwitter@kanoka0428undefined,undefinedtwitter@meshi_daneundefined,undefined<aundefinedhref='mailto:twitter@dodoMMD'>twitter@dodoMMD</a>","thumb":"//i.iwara.tv/sites/default/files/styles/thumbnail/public/videos/thumbnails/22244/thumbnail-22244_0001.png?itok=ZwPdGa-6","download":"https://www.iwara.tv/api/video/ojBZfbMLfNjO2Mb","origin":"https://www.iwara.tv/videos/ojBZfbMLfNjO2Mb"}