{"title":"【MMD】妖精リンで星屑サテライト【ray-MMD】","author":"KOBA","description":"ray-MMD1.0.9テスト兼用undefined1920x1080undefined30fps<br>ようつべ（1080p)undefinedundefined<aundefinedhref='https://youtu.be/-R9GTBzOq0s'>https://youtu.be/-R9GTBzOq0s</a><br>本家様:undefinedすこっぷ樣<br><aundefinedhref='http://www.nicovideo.jp/watch/sm8460426'>http://www.nicovideo.jp/watch/sm8460426</a><br>振付：ぴのぴ様undefined<br><aundefinedhref='http://www.nicovideo.jp/watch/sm27102075'>http://www.nicovideo.jp/watch/sm27102075</a><br>トレス元：さつき様<br><aundefinedhref='http://www.nicovideo.jp/watch/smsm27375955'>http://www.nicovideo.jp/watch/smsm27375955</a><br>モーション:undefinedしろたび樣<br><aundefinedhref='http://www.nicovideo.jp/watch/sm29637003'>http://www.nicovideo.jp/watch/sm29637003</a>","thumb":"//i.iwara.tv/sites/default/files/styles/thumbnail/public/videos/thumbnails/94612/thumbnail-94612_0003.jpg?itok=qrCTwZBs","download":"https://www.iwara.tv/api/video/pdjeofgoxujqal3x","origin":"https://www.iwara.tv/videos/pdjeofgoxujqal3x"}