{"title":"【東方MMD】ロンスカで月面レイヴァー（未調整版/default settings）【4K・リク応答】","author":"shbrtty2","description":"ご視聴ありがとうございます。リク応答編です。<br>ロンスカで低重力でハイファイを、というリクを頂き、月面相当の重力(0.16G)ではスカートがどれだけ舞うのか、やってみました。月面に因んでドクターえーりんとプリンセス輝夜をお迎えしました。当チャンネルデビューです8888～<br>今回のうｐでは、個々のスカートの物理設定は完全初期状態、どノーマルです。調整に時間が掛っているため、一旦未調整版を公開します。そして、ステージ奥にはとってもけしからんスクリーンがｗｗ","thumb":"//i.iwara.tv/sites/default/files/styles/thumbnail/public/video_embed_field_thumbnails/youtube/MCyfMOrooWo.jpg?itok=2hFFF5pD","download":"https://www.iwara.tv/api/video/qdl3bc735sl3jrrb","origin":"https://www.iwara.tv/videos/qdl3bc735sl3jrrb"}