{"title":"[mmd r-18] Special 2020- Goody time | Angels Lumine, Barbara and Amber ft. Venti and Diluc 4k 60fps","author":"genshistudio2","description":"R-18undefinedundefined4kundefined60fpsundefinedversion:<br><aundefinedhref='https://www.patreon.com/posts/45627355'>https://www.patreon.com/posts/45627355</a>","thumb":"//i.iwara.tv/sites/default/files/styles/thumbnail/public/video_embed_field_thumbnails/youtube/NcPUQSDXvFg.jpg?itok=4nfoULhZ","download":"https://www.iwara.tv/api/video/qzol8h8oqclqexra","origin":"https://www.iwara.tv/videos/qzol8h8oqclqexra"}