{"title":"[紳士向け] 黒森峰で極楽浄土R [Girls und Panzer]","author":"Deltarion","description":"<aundefinedhref='https://www.iwara.tv/videos/v5ew0cme62seevjzm'undefinedclass='bb-url'undefinedrel='nofollow'>旧作</a>のリメイクです。<br>RayMMDで透過って綺麗にできないのだけれど、実験的に動画編集ソフト側で透過してみました。<br>パンツ履いてるけどスカートから中が見えるって、紳士枠的な出来栄えになりましたが、どうでしょう？","thumb":"//i.iwara.tv/sites/default/files/styles/thumbnail/public/videos/thumbnails/559327/thumbnail-559327_0001.jpg?itok=YHyu6WYD","download":"https://www.iwara.tv/api/video/r1gapckqjmszrle1z","origin":"https://www.iwara.tv/videos/r1gapckqjmszrle1z"}