{"title":"【MMD】ツインテールなしの村雨がチカっとチカ千花！！","author":"昭和懐古おやぢ","description":"最初にこのモデルの作者のポンプ長さんとundefined改造されたバムさんに<br>一言お詫び申し上げます。m(_undefined_'m)undefinedundefined「村雨改二」の二次創作なのですが<br>昭和時代のおやぢとしては、いろいろ装飾のついたニーソよりシンプルな<br>ハイ・ソックスに萌える。そしてたまたまそういう改造している途中に<br>ツインテールをなんかの拍子で未表示扱いにしてしまったのですが、<br>ツインテールなしの村雨ちゃんundefinedこれはこれで非常に可愛いやん！<br>とう事で、作者のポンプ長さんとundefined改造されたバムさんに対して誠に失礼<br>な状態での公開となったことを一言お詫び申し上げます。","thumb":"//i.iwara.tv/sites/default/files/styles/thumbnail/public/videos/thumbnails/489330/thumbnail-489330_0003.jpg?itok=F-9nwpaL","download":"https://www.iwara.tv/api/video/rmv6lskdr4iz1mwlp","origin":"https://www.iwara.tv/videos/rmv6lskdr4iz1mwlp"}