{"title":"【MMD】SeeU ~Belly Dancer~ [DL Model in Description]","author":"RoryChan","description":"MODEL(DL):<br>SeeU→undefined<aundefinedhref='https://youtu.be/TnM5Ck63QLQ'>https://youtu.be/TnM5Ck63QLQ</a><br>Motion/Camera:undefinedKimagure<br>Stage:undefinedjuandiego245","thumb":"//i.iwara.tv/sites/default/files/styles/thumbnail/public/videos/thumbnails/1854664/thumbnail-1854664_0001.jpg?itok=DyyshsQp","download":"https://www.iwara.tv/api/video/vj8dvtm0z7uey4akg","origin":"https://www.iwara.tv/videos/vj8dvtm0z7uey4akg"}