{"title":"Lamb - Luka","author":"Alexeria","description":"-Model:undefined<aundefinedhref='http://ecchi.iwara.tv/images/luka-model-dl'>http://ecchi.iwara.tv/images/luka-model-dl</a><br>-Motion,undefinedcamera,undefinedWAV:undefined<aundefinedhref='http://tstorage.info/uo5ylmj0zcju'>http://tstorage.info/uo5ylmj0zcju</a><br>-Stage:undefined<aundefinedhref='https://bowlroll.net/file/147802'>https://bowlroll.net/file/147802</a><br>-Effects:<br>Raycast<br>Diffusionundefined7<br>Dust","thumb":"//i.iwara.tv/sites/default/files/styles/thumbnail/public/videos/thumbnails/290942/thumbnail-290942_0003.jpg?itok=NAI_SgqY","download":"https://www.iwara.tv/api/video/woq8zfr2l5cyywrx0","origin":"https://www.iwara.tv/videos/woq8zfr2l5cyywrx0"}