{"title":"プリンツ・オイゲン  ウサギのダンス [MMDアズールレーン]","author":"OAKI","description":"明るくしすぎたかな<br>Modelundefined:undefined<aundefinedhref='https://www.deviantart.com/xcallme-luxx/art/MMD-Prinz-Eugen-DL-835036224'>https://www.deviantart.com/xcallme-luxx/art/MMD-Prinz-Eugen-DL-835036224</a><br>Motionundefined:undefined<aundefinedhref='https://bowlroll.net/file/152699'>https://bowlroll.net/file/152699</a>undefined(pass:undefinedgiftundefined)<br>Musicundefined:undefined<aundefinedhref='https://www.nicovideo.jp/watch/sm11822274'>https://www.nicovideo.jp/watch/sm11822274</a><br>Effectundefined:undefinedEffectundefined:undefined「Ray-MMDundefined-undefined1.5.0」<aundefinedhref='https://github.com/ray-cast/ray-mmd'>https://github.com/ray-cast/ray-mmd</a><br>[ぬるてかシェーダー]<aundefinedhref='https://bowlroll.net/file/16903'>https://bowlroll.net/file/16903</a><br>[HgSAO]undefined<aundefinedhref='https://harigane.at.webry.info/201010/article_1.html'>https://harigane.at.webry.info/201010/article_1.html</a>undefined(pageundefined2)<br>[undefined空中に漂う埃エフェクト]undefined<aundefinedhref='https://bowlroll.net/file/18971'>https://bowlroll.net/file/18971</a>","thumb":"//i.iwara.tv/sites/default/files/styles/thumbnail/public/videos/thumbnails/1716771/thumbnail-1716771_0004.jpg?itok=fgKwLRtB","download":"https://www.iwara.tv/api/video/wp726h1zdbsqmlzzk","origin":"https://www.iwara.tv/videos/wp726h1zdbsqmlzzk"}