{"title":"タレ目の少女で「おじゃま虫」 / Green hair girl - Ojama mushi","author":"MikuMikuDancer","description":"Musicundefined:undefined【初音ミク】おじゃま虫【オリジナル曲】<br><aundefinedhref='http://www.nicovideo.jp/watch/sm22872605'>http://www.nicovideo.jp/watch/sm22872605</a>","thumb":"//i.iwara.tv/sites/default/files/styles/thumbnail/public/videos/thumbnails/199494/thumbnail-199494_0004.jpg?itok=qQp7sbNq","download":"https://www.iwara.tv/api/video/xqkneikbwbiwz1gor","origin":"https://www.iwara.tv/videos/xqkneikbwbiwz1gor"}