{"title":"Conqueror/由良改二【艦これ】Take2.2020.11.20update","author":"Youkainekotsurushi","description":"転載禁止undefined<br>Doundefinednotundefinedre-uploadundefinedmyundefinedvideosundefinedtoundefinedotherundefinedwebsite<br>禁止转载<br>素材提供者様、見てくれた方、ありがとうございます。<br>■データ配布元動画<br><aundefinedhref='https://youtu.be/C3E5fb39xcs'>https://youtu.be/C3E5fb39xcs</a><br><aundefinedhref='https://www.nicovideo.jp/watch/so34711771'>https://www.nicovideo.jp/watch/so34711771</a><br>2020.11.20undefined設定変更、ビットレート変更","thumb":"//i.iwara.tv/sites/default/files/styles/thumbnail/public/videos/thumbnails/1285064/thumbnail-1285064_0014.jpg?itok=7JCeBB2d","download":"https://www.iwara.tv/api/video/y1v60tvvwdso7wy3k","origin":"https://www.iwara.tv/videos/y1v60tvvwdso7wy3k"}